wordcluster/__init__.py
wordcluster-0.1.2.dist-info/LICENSE
wordcluster-0.1.2.dist-info/METADATA
wordcluster-0.1.2.dist-info/WHEEL
wordcluster-0.1.2.dist-info/top_level.txt
wordcluster-0.1.2.dist-info/RECORD
