Metadata-Version: 2.1
Name: wordcluster
Version: 0.1.2
Summary: A algoirthm for clustering similar words in a list
Home-page: 
Author: Dr. Suat ATAN
Author-email: suatatan@gmail.com
License: MIT
Requires-Python: >=3.6
License-File: LICENSE
